jsonwspclient/__init__.py
jsonwspclient/jsonwspclient.py
jsonwspclient/jsonwspexceptions.py
jsonwspclient/jsonwspmultipart.py
jsonwspclient/jsonwspresponse.py
jsonwspclient/jsonwspservice.py
jsonwspclient/jsonwsputils.py
jsonwspclient/requirements.txt
jsonwspclient-2.1.2.dist-info/LICENSE.txt
jsonwspclient-2.1.2.dist-info/WHEEL
jsonwspclient-2.1.2.dist-info/METADATA
jsonwspclient-2.1.2.dist-info/RECORD
